FLIP_FLOP/JKflipflop/JKflip_flop.v
module JKflip_flop (
  input clk, J, K,  
  output reg q,
  output q_bar
);

  assign q_bar = ~q;

  always @(posedge clk) begin
    case ({J, K})
      2'b00: q = q;      // No change
      2'b01: q = 1'b0;   // Reset
      2'b10: q = 1'b1;   // Set
      2'b11: q = ~q;     // Toggle
    endcase
  end
endmodule

FLIP_FLOP/JKflipflop/JKflip_flopTB.v
module JKflip_flopTB;
    reg clk, J, K;
    wire q, q_bar;

    JKflip_flop uut (.clk(clk), .J(J), .K(K), .q(q), .q_bar(q_bar));

    integer i;

    // Clock generation
    initial begin
        clk = 0;
        forever #5 clk = ~clk;
    end

    initial begin
        $dumpfile("JKflip_flop.vcd");
        $dumpvars(0, JKflip_flopTB);
    $monitor("t=%0t | clk=%b | J=%b K=%b | q=%b qb=%b", $time, clk, J, K, q, q_bar);

        for (i = 0; i < 4; i = i + 1) begin
            {J,K}=i;
            #40; 
        end
        $finish;
    end
endmodule

FLIP_FLOP/JKflipflop/JKflip_flop.vcd
$date
	Wed Oct 01 19:25:43 2025
$end
$version
	Icarus Verilog
$end
$timescale
	1s
$end
$scope module JKflip_flopTB $end
$var wire 1 ! q $end
$var wire 1 " q_bar $end
$var reg 1 # J $end
$var reg 1 $ K $end
$var reg 1 % clk $end
$var integer 32 & i [31:0] $end
$scope module uut $end
$var wire 1 ' J $end
$var wire 1 ( K $end
$var wire 1 ) clk $end
$var wire 1 " q_bar $end
$var reg 1 * q $end
$upscope $end
$upscope $end
$enddefinitions $end
#0
$dumpvars
x*
0)
0(
0'
b0 &
0%
0$
0#
x"
x!
$end
#5
1%
1)
#10
0%
0)
#15
1%
1)
#20
0%
0)
1$
1(
b1 &
#25
1"
0*
0!
1%
1)
#30
0%
0)
#35
1%
1)
#40
0%
0)
1#
1'
0$
0(
b10 &
#45
0"
1*
1!
1%
1)
#50
0%
0)
#55
1%
1)
#60
0%
0)
1$
1(
b11 &
#65
1"
0*
0!
1%
1)
#70
0%
0)
#75
0"
1*
1!
1%
1)
#80
0%
0)
b100 &
