FLIP_FLOP/JKflipflop/M_JK_flipflop.v
module master_JK_FLIPFLOP( 
input j,k,clk,rst,
output reg q,q_bar
);
reg master_q;

always @(posedge clk or posedge rst) begin
    if(rst)
    master_q <=0;
    else begin
        case({j,k})
            2'b00: master_q <= master_q;   2'b01:master_q <= 0;  
            2'b10 :master_q <= 1;          2'b11: master_q <= ~master_q;           
        endcase 
end
end

always @(negedge clk or posedge rst)
begin
    if(rst)begin
        q<=0;
        q_bar<=1;
    end else begin
        q <= master_q;
        q_bar <= ~master_q;
    end
end

endmodule

FLIP_FLOP/JKflipflop/M_JK_flipflopTB.v
module master_JK_FLIPFLOPTB();

    reg j,k, clk, rst;
    wire q, q_bar;

    master_JK_FLIPFLOP uut(.j(j),.k(k),.clk(clk),.rst(rst),.q(q),.q_bar(q_bar));

    initial begin
        clk =0;
        forever  #5 clk = ~clk;
    end

    initial begin

        $dumpfile("master_JK_FLIPFLOP.vcd");
        $dumpvars(0,master_JK_FLIPFLOPTB );
        $monitor("time=%t,clk=%b| j=%b, k=%b| q=%b, q_bar=%b",$time,clk,j,k,q,q_bar);

        rst=1;j =0;k=0; #10;
        rst =0;

        j=0;k=0; #10;
        j=0;k=1; #10;
        j=1;k=0; #10;
        j=1;k=1; #15;

        $finish;
    end
endmodule

FLIP_FLOP/JKflipflop/master_JK_FLIPFLOP.vcd
$date
	Fri Oct 03 13:06:54 2025
$end
$version
	Icarus Verilog
$end
$timescale
	1s
$end
$scope module master_JK_FLIPFLOPTB $end
$var wire 1 ! q $end
$var wire 1 " q_bar $end
$var reg 1 # clk $end
$var reg 1 $ j $end
$var reg 1 % k $end
$var reg 1 & rst $end
$scope module uut $end
$var wire 1 ' clk $end
$var wire 1 ( j $end
$var wire 1 ) k $end
$var wire 1 * rst $end
$var reg 1 + master_q $end
$var reg 1 , q $end
$var reg 1 - q_bar $end
$upscope $end
$upscope $end
$enddefinitions $end
#0
$dumpvars
1-
0,
0+
1*
0)
0(
0'
1&
0%
0$
0#
1"
0!
$end
#5
1#
1'
#10
0#
0'
0&
0*
#15
1#
1'
#20
0#
0'
1%
1)
#25
1#
1'
#30
0#
0'
0%
0)
1$
1(
#35
1+
1#
1'
#40
0-
0"
1,
1!
0#
0'
1%
1)
#45
0+
1#
1'
#50
1-
1"
0,
0!
0#
0'
#55
1+
1#
1'
