COUNTERS/RING/Ring_counter.v
module ring_counter(
    input clock, input reset,
    output [3:0] out,
    output reg [3:0] q);

    always @(posedge clock) begin
        if (reset)
            q <= 4'b0001;
        else begin
            q[3] <= q[2];
            q[2] <= q[1];
            q[1] <= q[0];
            q[0] <= q[3];
        end
    end

    assign out = q;

endmodule

COUNTERS/RING/Ring_counterTB.v
module ring_counter_tb();
    reg clock , reset;
    wire [3:0] q;

    ring_counter uut(
        .clock(clock),
        .reset(reset),
        .q(q)
    );

    initial begin
          clock = 0;
        forever #5 clock = ~clock;
    end

    initial begin
        $dumpfile("Ring_counter.vcd");
        $dumpvars(0, ring_counter_tb);
        
        $monitor("Time=%t,q=%b", $time,q);

        reset = 1;
        #10 reset = 0;
        #100;
        $finish;
    end
endmodule

COUNTERS/RING/Ring_counter.vcd
$date
	Fri Oct 17 20:04:59 2025
$end
$version
	Icarus Verilog
$end
$timescale
	1s
$end
$scope module ring_counter_tb $end
$var wire 4 ! q [3:0] $end
$var reg 1 " clock $end
$var reg 1 # reset $end
$scope module uut $end
$var wire 1 $ clock $end
$var wire 4 % out [3:0] $end
$var wire 1 & reset $end
$var reg 4 ' q [3:0] $end
$upscope $end
$upscope $end
$enddefinitions $end
#0
$dumpvars
bx '
1&
bx %
0$
1#
0"
bx !
$end
#5
b1 '
b1 %
b1 !
1"
1$
#10
0"
0$
0#
0&
#15
b10 %
b10 !
b10 '
1"
1$
#20
0"
0$
#25
b100 %
b100 !
b100 '
1"
1$
#30
0"
0$
#35
b1000 '
b1000 %
b1000 !
1"
1$
#40
0"
0$
#45
b1 '
b1 %
b1 !
1"
1$
#50
0"
0$
#55
b10 %
b10 !
b10 '
1"
1$
#60
0"
0$
#65
b100 %
b100 !
b100 '
1"
1$
#70
0"
0$
#75
b1000 '
b1000 %
b1000 !
1"
1$
#80
0"
0$
#85
b1 '
b1 %
b1 !
1"
1$
#90
0"
0$
#95
b10 %
b10 !
b10 '
1"
1$
#100
0"
0$
#105
b100 %
b100 !
b100 '
1"
1$
