REGISTER/FIFO/Fifo_sync.v
module sync_fifo #(
    parameter DATA_WIDTH = 4,   // 4-bit data
    parameter FIFO_DEPTH = 4    // 4 elements
)(
    input wire clk, rst,wr_en, rd_en,
    input wire [DATA_WIDTH-1:0] data_in,
    output reg [DATA_WIDTH-1:0] data_out
);

    // FIFO memory
    reg [DATA_WIDTH-1:0] fifo_mem [0:FIFO_DEPTH-1];

    // Pointers
    reg [1:0] write_pointer;   
    reg [1:0] read_pointer;   
    reg [2:0] fifo_count;     

    always @(posedge clk) begin
        if (rst) begin
            write_pointer <= 0;
            read_pointer <= 0;
            fifo_count <= 0;
            data_out <= 0;
        end else begin
            // Write operation
            if (wr_en && (fifo_count < FIFO_DEPTH)) begin
                fifo_mem[write_pointer] <= data_in;
                write_pointer <= write_pointer + 1; 
            end

            // Read operation
            if (rd_en && (fifo_count > 0)) begin
                data_out <= fifo_mem[read_pointer];
                read_pointer <= read_pointer + 1; 
            end

            // Update fifo_count
            case ({wr_en && (fifo_count < FIFO_DEPTH), rd_en && (fifo_count > 0)})
                2'b10: fifo_count <= fifo_count + 1;  // write only
                2'b01: fifo_count <= fifo_count - 1;  // read only
                default: fifo_count <= fifo_count;  
            endcase
        end
    end

endmodule

REGISTER/FIFO/Fifo_syncTB.v
module tb_sync_fifo;
    reg clk; rst;write_enable; read_enable;
    reg [3:0] data_input;   
    wire [3:0] data_output;

    sync_fifo #(4, 4) fifo_inst (
        .clk(clk),
        .rst(rst),
        .wr_en(write_enable),
        .rd_en(read_enable),
        .data_in(data_input),
        .data_out(data_output)
    );
    initial clk = 0;
    always #5 clk = ~clk;

    initial begin
        rst = 1;
        write_enable = 0;
        read_enable = 0;
        data_input = 4'b0000;
          #10 rst = 0;  

        repeat (4) begin
            data_input = data_input + 1;  // 0001, 0010, 0011, 0100
            write_enable = 1;
            read_enable = 0;
            #10;
        end

        write_enable = 0;
        data_input = 4'b0101;
        write_enable = 1;
        #10; d
        write_enable = 0;

        repeat (2) begin
            read_enable = 1;
            #10;
        end

        read_enable = 0;
        data_input = 4'b0101;
        write_enable = 1;
        #10;
        write_enable = 0;
    
        read_enable = 1;
        repeat (3) #10;
        read_enable = 0;

        #20 $finish;
    end
    initial begin
        $monitor("Time=%t | CLK=%b RST=%b WR_EN=%b RD_EN=%b | DATA_IN=%b DATA_OUT=%b",
                  $time, clk, rst, write_enable, read_enable, data_input, data_output);
    end
    initial begin
        $dumpfile("sync_fifo_tb.vcd");
        $dumpvars(0, tb_sync_fifo);
    end

endmodule

REGISTER/FIFO/sync_fifo_tb.vcd
$date
	Tue Nov 18 16:05:23 2025
$end
$version
	Icarus Verilog
$end
$timescale
	1s
$end
$scope module tb_sync_fifo $end
$var wire 4 ! data_output [3:0] $end
$var reg 1 " clk $end
$var reg 4 # data_input [3:0] $end
$var reg 1 $ read_enable $end
$var reg 1 % rst $end
$var reg 1 & write_enable $end
$scope module fifo_inst $end
$var wire 1 ' clk $end
$var wire 4 ( data_in [3:0] $end
$var wire 1 ) rd_en $end
$var wire 1 * rst $end
$var wire 1 + wr_en $end
$var reg 4 , data_out [3:0] $end
$var reg 3 - fifo_count [2:0] $end
$var reg 2 . read_pointer [1:0] $end
$var reg 2 / write_pointer [1:0] $end
$upscope $end
$upscope $end
$enddefinitions $end
#0
$dumpvars
bx /
bx .
bx -
bx ,
0+
1*
0)
b0 (
0'
0&
1%
0$
b0 #
0"
bx !
$end
#5
b0 ,
b0 !
b0 -
b0 .
b0 /
1"
1'
#10
0"
0'
1&
1+
b1 #
b1 (
0%
0*
#15
b1 -
b1 /
1"
1'
#20
0"
0'
b10 #
b10 (
#25
b10 -
b10 /
1"
1'
#30
0"
0'
b11 #
b11 (
#35
b11 -
b11 /
1"
1'
#40
0"
0'
b100 #
b100 (
#45
b100 -
b0 /
1"
1'
#50
0"
0'
b101 #
b101 (
1&
1+
#55
1"
1'
#60
0"
0'
1$
1)
0&
0+
#65
b11 -
b1 .
b1 ,
b1 !
1"
1'
#70
0"
0'
#75
b10 -
b10 .
b10 ,
b10 !
1"
1'
#80
0"
0'
1&
1+
0$
0)
#85
b11 -
b1 /
1"
1'
#90
0"
0'
1$
1)
0&
0+
#95
b10 -
b11 .
b11 ,
b11 !
1"
1'
#100
0"
0'
#105
b1 -
b0 .
b100 ,
b100 !
1"
1'
#110
0"
0'
#115
b0 -
b1 .
b101 ,
b101 !
1"
1'
#120
0"
0'
0$
0)
