COUNTERS/JOHNSON/johnson_counter.v
module johnson_counter(out, reset, clock);
    input clock, reset;
    output [3:0] out;
    reg [3:0] q;
    always @(posedge clock)
    begin
        if(reset)
        q= 4'd0;
        else
        begin
            q[3]<=q[2];
            q[2]<=q[1];
            q[1]<=q[0];
            q[0]<=(~q[3]);
            end
            end
            assign out =q;
        endmodule

COUNTERS/JOHNSON/johnson_counterTB.v
module johnson_counter_tb();
    reg clock;
    reg reset;
    wire [3:0] out;
    johnson_counter uut(
        .clock(clock),
        .reset(reset),
        .out(out)
    );

    initial begin
        clock =0;
        forever #5 clock= ~clock;
        $finish;
        end

        initial begin
        $dumpfile("johnson_counter.vcd");
        $dumpvars(0, johnson_counter_tb);
            reset =1;#10;
            reset = 0;
            #100
        $finish;
        end

        initial begin
            $monitor("Time=%t, clock=%b,Reset=%b, Output=%b",$time, clock, reset, out);
        end
    endmodule

COUNTERS/JOHNSON/johnson_counter.vcd
$date
	Wed Oct 15 07:06:29 2025
$end
$version
	Icarus Verilog
$end
$timescale
	1s
$end
$scope module johnson_counter_tb $end
$var wire 4 ! out [3:0] $end
$var reg 1 " clock $end
$var reg 1 # reset $end
$scope module uut $end
$var wire 1 $ clock $end
$var wire 4 % out [3:0] $end
$var wire 1 & reset $end
$var reg 4 ' q [3:0] $end
$upscope $end
$upscope $end
$enddefinitions $end
#0
$dumpvars
bx '
1&
bx %
0$
1#
0"
bx !
$end
#5
b0 '
b0 !
b0 %
1"
1$
#10
0"
0$
0#
0&
#15
b1 !
b1 %
b1 '
1"
1$
#20
0"
0$
#25
b11 !
b11 %
b11 '
1"
1$
#30
0"
0$
#35
b111 !
b111 %
b111 '
1"
1$
#40
0"
0$
#45
b1111 '
b1111 !
b1111 %
1"
1$
#50
0"
0$
#55
b1110 !
b1110 %
b1110 '
1"
1$
#60
0"
0$
#65
b1100 !
b1100 %
b1100 '
1"
1$
#70
0"
0$
#75
b1000 !
b1000 %
b1000 '
1"
1$
#80
0"
0$
#85
b0 '
b0 !
b0 %
1"
1$
#90
0"
0$
#95
b1 !
b1 %
b1 '
1"
1$
#100
0"
0$
#105
b11 !
b11 %
b11 '
1"
1$
