SUBTRACTOR/subtractor.v

// Half Subtractor Module
// Performs subtraction of two single bits: a - b
// Outputs:
//   difference = a - b
//   borrow = 1 if a < b, else 0
module half_subtractor(
    input a,         // Minuend bit
    input b,         // Subtrahend bit
    output difference, // Difference output
    output borrow      // Borrow output
);
    // Difference is XOR of a and b
    assign difference = a ^ b;
    // Borrow is set if a is 0 and b is 1
    assign borrow = (~a) & b;
endmodule


// Full Subtractor Module
// Performs subtraction of three bits: a - b - bin
// Inputs:
//   a    = Minuend bit
//   b    = Subtrahend bit
//   bin  = Borrow in
// Outputs:
//   difference = a - b - bin
//   borrow     = Borrow out
module full_subtractor(
    input a,         // Minuend bit
    input b,         // Subtrahend bit
    input bin,       // Borrow in
    output difference, // Difference output
    output borrow      // Borrow output
);
    wire w1, w2, w3; // Internal wires
    // First half subtractor: a - b
    half_subtractor h1( a, b, w1, w2 );
    // Second half subtractor: (a-b) - bin
    half_subtractor h2( w1, bin, difference, w3 );
    // Borrow out is OR of both borrows
    assign borrow = w2 | w3;
endmodule

SUBTRACTOR/subtractorTB.v

// Testbench for Full Subtractor
module full_subtractorTB();
    reg a, b, bin;           // Test inputs
    wire difference, borrow; // Outputs from DUT
    integer i;               // Loop variable

    // Instantiate the Device Under Test (DUT)
    full_subtractor dut(
        .a(a),
        .b(b),
        .bin(bin),
        .difference(difference),
        .borrow(borrow)
    );

    initial begin
        // Set up VCD file for waveform viewing
        $dumpfile("subtractor.vcd");
        $dumpvars(0, full_subtractorTB);

        // Apply all input combinations (a, b, bin)
        for(i=0; i<8; i=i+1) begin
            {a, b, bin} = i; // Assign bits of i to a, b, bin
            #10;            // Wait 10 time units
            // Display current values and outputs
            $display("time = %0t | a=%b | b=%b | bin=%b | difference=%b | borrow=%b", $time, a, b, bin, difference, borrow);
        end
        $finish; // End simulation
    end
endmodule

SUBTRACTOR/subtractor.vcd
$date
	Sat Sep 13 22:12:14 2025
$end
$version
	Icarus Verilog
$end
$timescale
	1s
$end
$scope module full_subtractorTB $end
$var wire 1 ! borrow $end
$var wire 1 " difference $end
$var reg 1 # a $end
$var reg 1 $ b $end
$var reg 1 % bin $end
$var integer 32 & i [31:0] $end
$scope module dut $end
$var wire 1 ' a $end
$var wire 1 ( b $end
$var wire 1 ) bin $end
$var wire 1 ! borrow $end
$var wire 1 " difference $end
$var wire 1 * w1 $end
$var wire 1 + w2 $end
$var wire 1 , w3 $end
$scope module h1 $end
$var wire 1 ' a $end
$var wire 1 ( b $end
$var wire 1 + borrow $end
$var wire 1 * difference $end
$upscope $end
$scope module h2 $end
$var wire 1 * a $end
$var wire 1 ) b $end
$var wire 1 , borrow $end
$var wire 1 " difference $end
$upscope $end
$upscope $end
$upscope $end
$enddefinitions $end
#0
$dumpvars
0,
0+
0*
0)
0(
0'
b0 &
0%
0$
0#
0"
0!
$end
#10
1!
1"
1,
1%
1)
b1 &
#20
1*
1+
1"
0,
1$
1(
0%
0)
b10 &
#30
0"
1%
1)
b11 &
#40
0!
0+
1"
1#
1'
0$
0(
0%
0)
b100 &
#50
0"
1%
1)
b101 &
#60
0*
0"
1$
1(
0%
0)
b110 &
#70
1!
1"
1,
1%
1)
b111 &
#80
b1000 &
