SEQUENCE_DETECTOR/mealy/mealy.v

module mealy_fsm (
    input clk,
    input reset,
    input in,
    output reg out,
    output [1:0] state   
);

  
    parameter S0 = 2'b00;
    parameter S1 = 2'b01;
    parameter S2 = 2'b10;

    reg [1:0] current_state, next_state;
    assign state = current_state;

    always @(posedge clk or posedge reset) begin
        if (reset)
            current_state <= S0;
        else
            current_state <= next_state;
    end

    always @(*) begin
    next_state = S0;
        out = 1'b0;

        case (current_state)
            S0: begin
                if (in) begin
                    next_state = S1;
                    out = 1'b0;
                end 
                else begin
                    next_state = S0;
                    out = 1'b0;
                end
            end

            S1: begin
                if (in) begin
                    next_state = S1;
                    out = 1'b0;
                end
                 else begin
                    next_state = S2;
                    out = 1'b0;
                end
            end

            S2: begin
                if (in) begin
                    // matched 101 = output immediately
                    next_state = S1;
                    out = 1'b1;
                end 
                else begin
                    next_state = S0;
                    out = 1'b0;
                end
            end

            default: begin
                next_state = S0;
                out = 1'b0;
            end
        endcase
    end

endmodule

SEQUENCE_DETECTOR/mealy/mealyTB.v
`timescale 1ns / 1ps
module mealy_fsm_tb;
    reg clk; reg reset; reg in; wire out; wire [1:0] state;
    integer i;
    reg seq_array [0:7]; 

    mealy_fsm uut (.clk(clk), .reset(reset), .in(in), .out(out), .state(state));

    initial begin clk = 0; forever #5 clk = ~clk; end

    initial begin
        $dumpfile("mealy_tb.vcd");
        $dumpvars(0, mealy_fsm_tb);
        reset = 1; in = 0;
        //sequence: 1,0,1,0,1,1,0,1 
        seq_array[0] = 1; seq_array[1] = 0; seq_array[2] = 1; seq_array[3] = 0;
        seq_array[4] = 1; seq_array[5] = 1; seq_array[6] = 0; seq_array[7] = 1;
        #15 reset = 0;

        for (i = 0; i < 8; i = i + 1) begin
            @(posedge clk);
            in = seq_array[i];#1; 
            $display("T=%0t | reset=%b | in=%b | state=%b | out=%b", $time, reset, in, state, out);
        end

        #20; $finish;
    end

endmodule

SEQUENCE_DETECTOR/mealy/mealy_tb.vcd
$date
	Wed Nov 05 14:16:16 2025
$end
$version
	Icarus Verilog
$end
$timescale
	1ps
$end
$scope module mealy_fsm_tb $end
$var wire 1 ! out $end
$var wire 2 " state [1:0] $end
$var reg 1 # clk $end
$var integer 32 $ i [31:0] $end
$var reg 1 % in $end
$var reg 1 & reset $end
$scope module uut $end
$var wire 1 ' clk $end
$var wire 1 ( in $end
$var wire 1 ) reset $end
$var wire 2 * state [1:0] $end
$var reg 2 + current_state [1:0] $end
$var reg 2 , next_state [1:0] $end
$var reg 1 - out $end
$upscope $end
$upscope $end
$enddefinitions $end
#0
$dumpvars
0-
b0 ,
b0 +
b0 *
1)
0(
0'
1&
0%
bx $
0#
b0 "
0!
$end
#5000
1#
1'
#10000
0#
0'
#15000
b1 ,
1%
1(
1#
1'
b0 $
0&
0)
#16000
b1 $
#20000
0#
0'
#25000
b1 +
b1 "
b1 *
b10 ,
0%
0(
1#
1'
#26000
b10 $
#30000
0#
0'
#35000
1-
1!
b10 +
b10 "
b10 *
b1 ,
1%
1(
1#
1'
#36000
b11 $
#40000
0#
0'
#45000
b1 +
b1 "
b1 *
0-
0!
b10 ,
0%
0(
1#
1'
#46000
b100 $
#50000
0#
0'
#55000
1-
1!
b10 +
b10 "
b10 *
b1 ,
1%
1(
1#
1'
#56000
b101 $
#60000
0#
0'
#65000
0-
0!
b1 ,
b1 +
b1 "
b1 *
1#
1'
#66000
b110 $
#70000
0#
0'
#75000
b10 ,
0%
0(
1#
1'
#76000
b111 $
#80000
0#
0'
#85000
1-
1!
b10 +
b10 "
b10 *
b1 ,
1%
1(
1#
1'
#86000
b1000 $
#90000
0#
0'
#95000
0-
0!
b1 ,
b1 +
b1 "
b1 *
1#
1'
