SEQUENCE_DETECTOR/moore/Moore_fsm.v
`timescale 1ns / 1ps
module moore_fsm (
    input clk,
    input reset,
    input in,
    output reg out
);

 
    parameter S0 = 2'b00;
    parameter S1 = 2'b01;
    parameter S2 = 2'b10;
    parameter S3 = 2'b11;

    reg [1:0] current_state, next_state;

    // State register
    always @(posedge clk or posedge reset) begin
        if (reset)
            current_state <= S0;
        else
            current_state <= next_state;
    end

    // Next state logic
    always @(*) begin
        case (current_state)
            S0: if (in) next_state = S1; else next_state = S0;
            S1: if (in) next_state = S1; else next_state = S2;
            S2: if (in) next_state = S3; else next_state = S0;
            S3: if (in) next_state = S1; else next_state = S2;
            default: next_state = S0;
        endcase
    end

    // Output logic 
    always @(*) begin
        case (current_state)
            S3: out = 1'b1;
            default: out = 1'b0;
        endcase
    end

endmodule

SEQUENCE_DETECTOR/moore/Moore_fsmTB.v
`timescale 1ns / 1ps

module moore_fsm_tb;
    reg clk;reg reset;
    reg in;    wire out;

    moore_fsm uut (
        .clk(clk),
        .reset(reset),
        .in(in),
        .out(out)
    );

    always #5 clk = ~clk;

    initial begin
    clk = 0;    reset = 1; in = 0;
    #10 reset = 0;

        //Test pattern: 1 0 1 1 0 1
        #10 in = 1;
        #10 in = 0;
        #10 in = 1; 
        #10 in = 1;
        #10 in = 0;
        #10 in = 1; 
        #20;

        $finish;
    end

    initial begin
         $dumpfile("moore_fsm_tb.vcd");
        $dumpvars(0, moore_fsm_tb);
        $monitor("T=%t | reset=%b | in=%b | out=%b", $time, reset, in, out);
    end

endmodule

SEQUENCE_DETECTOR/moore/moore_fsm_tb.vcd
$date
	Mon Nov 03 17:55:39 2025
$end
$version
	Icarus Verilog
$end
$timescale
	1ps
$end
$scope module moore_fsm_tb $end
$var wire 1 ! out $end
$var reg 1 " clk $end
$var reg 1 # in $end
$var reg 1 $ reset $end
$scope module uut $end
$var wire 1 % clk $end
$var wire 1 & in $end
$var wire 1 ' reset $end
$var reg 2 ( current_state [1:0] $end
$var reg 2 ) next_state [1:0] $end
$var reg 1 * out $end
$upscope $end
$upscope $end
$enddefinitions $end
#0
$dumpvars
0*
b0 )
b0 (
1'
0&
0%
1$
0#
0"
0!
$end
#5000
1"
1%
#10000
0"
0%
0$
0'
#15000
1"
1%
#20000
b1 )
0"
0%
1#
1&
#25000
b1 (
1"
1%
#30000
b10 )
0"
0%
0#
0&
#35000
b0 )
b10 (
1"
1%
#40000
b11 )
0"
0%
1#
1&
#45000
1*
1!
b1 )
b11 (
1"
1%
#50000
0"
0%
#55000
0*
0!
b1 (
1"
1%
#60000
b10 )
0"
0%
0#
0&
#65000
b0 )
b10 (
1"
1%
#70000
b11 )
0"
0%
1#
1&
#75000
1*
1!
b1 )
b11 (
1"
1%
#80000
0"
0%
#85000
0*
0!
b1 (
1"
1%
