ADDER/fullAdder.v

module full_adder(
	a,
	b,
	c_in,
	sum,
	carry_out
);
input a;
input b;
input c_in;
output sum;
output carry_out;

assign sum = a ^ b ^ c_in;
assign carry_out = (a & b) | (a & c_in) | (c_in & b);

endmodule

ADDER/fullAdderTB.v
`timescale 1ns/ 1ps
module tb_full_adder;

reg a, b, c_in;
wire sum, carry_out;
full_adder dut(a, b, c_in, sum, carry_out);

initial begin 
$dumpfile("fullAdderTB.vcd");
$dumpvars(0, tb_full_adder);
end


initial begin
$display("Testing full adder");
$monitor( "a = %b, b =%b, c_in = %b, sum = %b, carry_out = %b", a,b,c_in, sum, carry_out);

a = 0; b = 0; c_in = 0; #10;
a = 0; b = 0; c_in = 1; #10;
a = 0; b = 1; c_in = 0; #10;
a = 0; b = 1; c_in = 1; #10;
a = 1; b = 0; c_in = 0; #10;
a = 1; b = 0; c_in = 1; #10;
a = 1; b = 1; c_in = 0; #10;
a = 1; b = 1; c_in = 1; #10;

$finish;
end
endmodule

ADDER/fullAdderTB.vcd
$date
	Fri Sep 12 21:28:11 2025
$end
$version
	Icarus Verilog
$end
$timescale
	1ps
$end
$scope module tb_full_adder $end
$var wire 1 ! carry_out $end
$var wire 1 " sum $end
$var reg 1 # a $end
$var reg 1 $ b $end
$var reg 1 % c_in $end
$scope module dut $end
$var wire 1 & a $end
$var wire 1 ' b $end
$var wire 1 ( c_in $end
$var wire 1 ! carry_out $end
$var wire 1 " sum $end
$upscope $end
$upscope $end
$enddefinitions $end
#0
$dumpvars
0(
0'
0&
0%
0$
0#
0"
0!
$end
#10000
1"
1%
1(
#20000
0%
0(
1$
1'
#30000
1!
0"
1%
1(
#40000
0!
1"
0%
0(
0$
0'
1#
1&
#50000
1!
0"
1%
1(
#60000
0%
0(
1$
1'
#70000
1"
1%
1(
