MUX/mux.v
module mux_2_1(
    input select,i0,i1,
    output y);

    assign y = select? i1 : i0;
    
endmodule

MUX/muxTB.v
module mux_2_1tb();
    reg select, i0, i1;
    wire y;
    integer i;

        mux_2_1 dut (.select(select),.i0(i0),.i1(i1),.y(y));

    initial begin
        $dumpfile("mux.vcd");
        $dumpvars(0, mux_2_1tb);
        select = 0; i0 = 0; i1 = 0; 
        
        for(i=0; i<8; i=i+1) begin
            {select, i0, i1} = i;
            #10;
        end
    end

    initial 
    begin
    $monitor ("Time=%4t | select = %b | i0 = %b | i1 = %b | y = %b", $time, select, i0, i1, y);
    end
endmodule

MUX/mux.vcd
$date
	Wed Sep 17 19:59:55 2025
$end
$version
	Icarus Verilog
$end
$timescale
	1s
$end
$scope module mux_2_1tb $end
$var wire 1 ! y $end
$var integer 32 " i [31:0] $end
$var reg 1 # i0 $end
$var reg 1 $ i1 $end
$var reg 1 % select $end
$scope module dut $end
$var wire 1 & i0 $end
$var wire 1 ' i1 $end
$var wire 1 ( select $end
$var wire 1 ! y $end
$upscope $end
$upscope $end
$enddefinitions $end
#0
$dumpvars
0(
0'
0&
0%
0$
0#
b0 "
0!
$end
#10
1$
1'
b1 "
#20
1!
1#
1&
0$
0'
b10 "
#30
1$
1'
b11 "
#40
0!
1%
1(
0#
0&
0$
0'
b100 "
#50
1!
1$
1'
b101 "
#60
0!
1#
1&
0$
0'
b110 "
#70
1!
1$
1'
b111 "
#80
b1000 "
