COUNTERS/ASYNCHRONOUS/Async_counter.v
module async_counter(
    input clock,
    input reset,
    output reg [3:0]q
);
    
always @(posedge clock,posedge reset) begin
    
    if(reset)
    q<=4'b0000;
    else
    q<=q-1;
end
endmodule

COUNTERS/ASYNCHRONOUS/Async_counterTB.v
module async_counterTB();
    reg clock, reset;
    wire [3:0]q;

    async_counter dut (
    .clock(clock),    
    .reset(reset),
    .q(q)    
    );

    initial begin 
        clock = 1'b0;
        forever #5 clock = ~clock;
    end

    initial
    begin
        $dumpfile("Async_counter.vcd");
        $dumpvars(0, async_counterTB);
        #10;
        reset=1'b1;
        #10;
        reset = 1'b0;
        #150; $finish();
    end

    initial
    begin
        $monitor("Time =%t, clock=%b, reset=%b, q=%b",$time,clock,reset,q);
    end

endmodule

COUNTERS/ASYNCHRONOUS/Async_counter.vcd
$date
	Wed Oct 15 06:40:02 2025
$end
$version
	Icarus Verilog
$end
$timescale
	1s
$end
$scope module async_counterTB $end
$var wire 4 ! q [3:0] $end
$var reg 1 " clock $end
$var reg 1 # reset $end
$scope module dut $end
$var wire 1 $ clock $end
$var wire 1 % reset $end
$var reg 4 & q [3:0] $end
$upscope $end
$upscope $end
$enddefinitions $end
#0
$dumpvars
bx &
x%
0$
x#
0"
bx !
$end
#5
1"
1$
#10
b0 &
b0 !
0"
0$
1#
1%
#15
1"
1$
#20
0"
0$
0#
0%
#25
b1111 &
b1111 !
1"
1$
#30
0"
0$
#35
b1110 &
b1110 !
1"
1$
#40
0"
0$
#45
b1101 &
b1101 !
1"
1$
#50
0"
0$
#55
b1100 &
b1100 !
1"
1$
#60
0"
0$
#65
b1011 &
b1011 !
1"
1$
#70
0"
0$
#75
b1010 &
b1010 !
1"
1$
#80
0"
0$
#85
b1001 &
b1001 !
1"
1$
#90
0"
0$
#95
b1000 &
b1000 !
1"
1$
#100
0"
0$
#105
b111 &
b111 !
1"
1$
#110
0"
0$
#115
b110 &
b110 !
1"
1$
#120
0"
0$
#125
b101 &
b101 !
1"
1$
#130
0"
0$
#135
b100 &
b100 !
1"
1$
#140
0"
0$
#145
b11 &
b11 !
1"
1$
#150
0"
0$
#155
b10 &
b10 !
1"
1$
#160
0"
0$
#165
b1 &
b1 !
1"
1$
