COUNTERS/SYNCHRONOUS/sync_counter.v
module synchronous_counter(
    input clock,
    input reset,
    input load_enable,
    input [3:0] data_in,
    output reg [3:0] counter_value
);

always @(posedge clock)
begin
    if (reset)
        counter_value <= 4'b0000;
    else if (load_enable)
        counter_value <= data_in;
    else 
        counter_value <= counter_value - 1;
end
endmodule

COUNTERS/SYNCHRONOUS/sync_counter_tb.v
module sync_counter_tb;
    reg clock, reset;  reg [3:0] data_in; wire [3:0] counter_value; integer i;
    
    synchronous_counter uut (
        .clock(clock),
        .reset(reset),
        .data_in(data_in),
        .counter_value(counter_value)
    );
    initial begin
        clock = 0;
        forever #5 clock = ~clock;
    end

    task reset_input;
        begin
            reset = 1'b1; #10
            reset = 1'b0;
        end        
    endtask 

    task input_dut(input [3:0] j);
        begin
            data_in = j;
        end
   
    endtask
 
 initial begin
        $dumpfile("sync_counter.vcd");
        $dumpvars(0, sync_counter_tb);
       
        reset = 0;
        data_in = 4'b0000;
       
        reset_input();
        for(i=0; i<4; i=i+1)begin
            @(negedge clock);
            input_dut(1 <<i);
    end
       #50 $finish;
    end
    initial $monitor("time=%t clock=%b | reset=%b  data_in=%b | counter_value=%b", $time,clock, reset,data_in, counter_value);
endmodule

COUNTERS/SYNCHRONOUS/sync_counter.vcd
$date
	Fri Oct 10 09:38:02 2025
$end
$version
	Icarus Verilog
$end
$timescale
	1s
$end
$scope module sync_counter_tb $end
$var wire 4 ! counter_value [3:0] $end
$var reg 1 " clock $end
$var reg 4 # data_in [3:0] $end
$var integer 32 $ i [31:0] $end
$var reg 1 % reset $end
$scope module uut $end
$var wire 1 & clock $end
$var wire 4 ' data_in [3:0] $end
$var wire 1 ( load_enable $end
$var wire 1 ) reset $end
$var reg 4 * counter_value [3:0] $end
$upscope $end
$scope task input_dut $end
$var reg 4 + j [3:0] $end
$upscope $end
$scope task reset_input $end
$upscope $end
$upscope $end
$enddefinitions $end
#0
$dumpvars
bx +
bx *
1)
z(
b0 '
0&
1%
bx $
b0 #
0"
bx !
$end
#5
b0 *
b0 !
1"
1&
#10
b1 #
b1 '
b1 +
0"
0&
b1 $
0%
0)
#15
b1111 *
b1111 !
1"
1&
#20
b10 $
b10 #
b10 '
b10 +
0"
0&
#25
b1110 *
b1110 !
1"
1&
#30
b11 $
b100 #
b100 '
b100 +
0"
0&
#35
b1101 *
b1101 !
1"
1&
#40
b100 $
b1000 #
b1000 '
b1000 +
0"
0&
#45
b1100 *
b1100 !
1"
1&
#50
0"
0&
#55
b1011 *
b1011 !
1"
1&
#60
0"
0&
#65
b1010 *
b1010 !
1"
1&
#70
0"
0&
#75
b1001 *
b1001 !
1"
1&
#80
0"
0&
#85
b1000 *
b1000 !
1"
1&
