RIPPLE_ADDER/Ripple_carry_adder.v

module full_adder(input a, b, c, output sum, carry);
    assign sum = a ^ b ^ c;
    assign carry = (a & b) | (a & c) | (b & c); 
endmodule


module ripple_carry_adder(
     input [3:0] a, b,
     input c, 
     output [3:0] sum, 
     output carry);
     wire c1, c2, c3;
    full_adder fa0(   .a(a[0]), .b(b[0]), .c(c),    .sum(sum[0]), .carry(c1)
    );
    full_adder fa1(
        .a(a[1]), .b(b[1]), .c(c1),   .sum(sum[1]), .carry(c2)
    );
    full_adder fa2(
        .a(a[2]), .b(b[2]), .c(c2),   .sum(sum[2]), .carry(c3)
    );
    full_adder fa3(
        .a(a[3]), .b(b[3]), .c(c3),   .sum(sum[3]), .carry(carry)
    );
endmodule

RIPPLE_ADDER/Ripple_carry_adderTB.v
module ripple_carry_adderTB();
    reg [3:0] a, b;       reg c;               
    wire [3:0] sum;       wire carry;          
    integer i, j;        

    ripple_carry_adder dut(a, b, c, sum, carry);
    initial begin
    $dumpfile("ripple_carry_adder.vcd");
    $dumpvars(0, ripple_carry_adderTB, a, b, sum, carry);
        // Test with carry-in = 0
        c = 0;
        for(i = 0; i < 16; i = i + 1) begin
            for(j = 0; j < 16; j = j + 1) begin
                a = i; b = j;
                #10;
                $display("time = %t | a=%b | b=%b | c=%b | sum=%b | carry=%b", $time, a, b, c, sum, carry);
            end
        end
        // Test with carry-in = 1
        c = 1;
        for(i = 0; i < 16; i = i + 1) begin
            for(j = 0; j < 16; j = j + 1) begin
                a = i; b = j;
                #10;
                $display("time = %t | a=%b | b=%b | c=%b | sum=%b | carry=%b", $time, a, b, c, sum, carry);
            end
        end
        $finish;
    end
endmodule

RIPPLE_ADDER/ripple_carry_adder.vcd
$date
	Mon Sep 15 21:44:42 2025
$end
$version
	Icarus Verilog
$end
$timescale
	1s
$end
$scope module ripple_carry_adderTB $end
$var wire 1 ! carry $end
$var wire 4 " sum [3:0] $end
$var reg 4 # a [3:0] $end
$var reg 4 $ b [3:0] $end
$var reg 1 % c $end
$var integer 32 & i [31:0] $end
$var integer 32 ' j [31:0] $end
$scope module dut $end
$var wire 4 ( a [3:0] $end
$var wire 4 ) b [3:0] $end
$var wire 1 * c $end
$var wire 1 + c1 $end
$var wire 1 , c2 $end
$var wire 1 - c3 $end
$var wire 1 ! carry $end
$var wire 4 . sum [3:0] $end
$scope module fa0 $end
$var wire 1 / a $end
$var wire 1 0 b $end
$var wire 1 * c $end
$var wire 1 + carry $end
$var wire 1 1 sum $end
$upscope $end
$scope module fa1 $end
$var wire 1 2 a $end
$var wire 1 3 b $end
$var wire 1 + c $end
$var wire 1 , carry $end
$var wire 1 4 sum $end
$upscope $end
$scope module fa2 $end
$var wire 1 5 a $end
$var wire 1 6 b $end
$var wire 1 , c $end
$var wire 1 - carry $end
$var wire 1 7 sum $end
$upscope $end
$scope module fa3 $end
$var wire 1 8 a $end
$var wire 1 9 b $end
$var wire 1 - c $end
$var wire 1 ! carry $end
$var wire 1 : sum $end
$upscope $end
$upscope $end
$upscope $end
$enddefinitions $end
#0
$dumpvars
0:
09
08
07
06
05
04
03
02
01
00
0/
b0 .
0-
0,
0+
0*
b0 )
b0 (
b0 '
b0 &
0%
b0 $
b0 #
b0 "
0!
$end
#10
11
b1 "
b1 .
10
b1 $
b1 )
b1 '
#20
01
14
b10 "
b10 .
00
13
b10 $
b10 )
b10 '
#30
11
b11 "
b11 .
10
b11 $
b11 )
b11 '
#40
01
04
17
b100 "
b100 .
00
03
16
b100 $
b100 )
b100 '
#50
11
b101 "
b101 .
10
b101 $
b101 )
b101 '
#60
01
14
b110 "
b110 .
00
13
b110 $
b110 )
b110 '
#70
11
b111 "
b111 .
10
b111 $
b111 )
b111 '
#80
01
04
07
1:
b1000 "
b1000 .
00
03
06
19
b1000 $
b1000 )
b1000 '
#90
11
b1001 "
b1001 .
10
b1001 $
b1001 )
b1001 '
#100
01
14
b1010 "
b1010 .
00
13
b1010 $
b1010 )
b1010 '
#110
11
b1011 "
b1011 .
10
b1011 $
b1011 )
b1011 '
#120
01
04
17
b1100 "
b1100 .
00
03
16
b1100 $
b1100 )
b1100 '
#130
11
b1101 "
b1101 .
10
b1101 $
b1101 )
b1101 '
#140
01
14
b1110 "
b1110 .
00
13
b1110 $
b1110 )
b1110 '
#150
11
b1111 "
b1111 .
10
b1111 $
b1111 )
b1111 '
#160
04
07
0:
b1 "
b1 .
00
03
06
09
1/
b0 $
b0 )
b1 #
b1 (
b1 &
b0 '
#170
14
1+
01
b10 "
b10 .
10
b1 $
b1 )
b1 '
#180
0+
07
11
14
b11 "
b11 .
0,
00
13
b10 $
b10 )
b10 '
#190
17
1,
04
1+
01
b100 "
b100 .
10
b11 $
b11 )
b11 '
#200
0+
0:
11
04
0,
17
b101 "
b101 .
0-
00
03
16
b100 $
b100 )
b100 '
#210
14
1+
01
b110 "
b110 .
10
b101 $
b101 )
b101 '
#220
0:
0-
0+
17
11
14
b111 "
b111 .
0,
00
13
b110 $
b110 )
b110 '
#230
1:
1-
07
1,
04
1+
01
b1000 "
b1000 .
10
b111 $
b111 )
b111 '
#240
0+
11
04
0,
07
0-
1:
b1001 "
b1001 .
0!
00
03
06
19
b1000 $
b1000 )
b1000 '
#250
14
1+
01
b1010 "
b1010 .
10
b1001 $
b1001 )
b1001 '
#260
0+
07
11
14
b1011 "
b1011 .
0,
00
13
b1010 $
b1010 )
b1010 '
#270
17
1,
04
1+
01
b1100 "
b1100 .
10
b1011 $
b1011 )
b1011 '
#280
0!
0+
1:
11
04
0,
17
b1101 "
b1101 .
0-
00
03
16
b1100 $
b1100 )
b1100 '
#290
14
1+
01
b1110 "
b1110 .
10
b1101 $
b1101 )
b1101 '
#300
0!
1:
0-
0+
17
11
14
b1111 "
b1111 .
0,
00
13
b1110 $
b1110 )
b1110 '
#310
1!
0:
1-
07
1,
04
1+
01
b0 "
b0 .
10
b1111 $
b1111 )
b1111 '
#320
0,
14
0+
07
0-
0:
b10 "
b10 .
0!
00
03
06
09
0/
12
b0 $
b0 )
b10 #
b10 (
b10 &
b0 '
#330
11
b11 "
b11 .
10
b1 $
b1 )
b1 '
#340
17
1,
01
04
b100 "
b100 .
00
13
b10 $
b10 )
b10 '
#350
11
b101 "
b101 .
10
b11 $
b11 )
b11 '
#360
0,
0:
01
14
17
b110 "
b110 .
0-
00
03
16
b100 $
b100 )
b100 '
#370
11
b111 "
b111 .
10
b101 $
b101 )
b101 '
#380
1:
1-
07
1,
01
04
b1000 "
b1000 .
00
13
b110 $
b110 )
b110 '
#390
11
b1001 "
b1001 .
10
b111 $
b111 )
b111 '
#400
0,
01
14
07
0-
1:
b1010 "
b1010 .
0!
00
03
06
19
b1000 $
b1000 )
b1000 '
#410
11
b1011 "
b1011 .
10
b1001 $
b1001 )
b1001 '
#420
17
1,
01
04
b1100 "
b1100 .
00
13
b1010 $
b1010 )
b1010 '
#430
11
b1101 "
b1101 .
10
b1011 $
b1011 )
b1011 '
#440
0!
0,
1:
01
14
17
b1110 "
b1110 .
0-
00
03
16
b1100 $
b1100 )
b1100 '
#450
11
b1111 "
b1111 .
10
b1101 $
b1101 )
b1101 '
#460
1!
0:
1-
07
1,
01
04
b0 "
b0 .
00
13
b1110 $
b1110 )
b1110 '
#470
11
b1 "
b1 .
10
b1111 $
b1111 )
b1111 '
#480
0,
14
07
0-
0:
b11 "
b11 .
0!
00
03
06
09
1/
b0 $
b0 )
b11 #
b11 (
b11 &
b0 '
#490
17
1,
04
1+
01
b100 "
b100 .
10
b1 $
b1 )
b1 '
#500
0+
11
04
b101 "
b101 .
00
13
b10 $
b10 )
b10 '
#510
14
1+
01
b110 "
b110 .
10
b11 $
b11 )
b11 '
#520
0,
0+
0:
11
14
17
b111 "
b111 .
0-
00
03
16
b100 $
b100 )
b100 '
#530
1:
1-
07
1,
04
1+
01
b1000 "
b1000 .
10
b101 $
b101 )
b101 '
#540
0+
11
04
b1001 "
b1001 .
00
13
b110 $
b110 )
b110 '
#550
14
1+
01
b1010 "
b1010 .
10
b111 $
b111 )
b111 '
#560
0,
0+
11
14
07
0-
1:
b1011 "
b1011 .
0!
00
03
06
19
b1000 $
b1000 )
b1000 '
#570
17
1,
04
1+
01
b1100 "
b1100 .
10
b1001 $
b1001 )
b1001 '
#580
0+
11
04
b1101 "
b1101 .
00
13
b1010 $
b1010 )
b1010 '
#590
14
1+
01
b1110 "
b1110 .
10
b1011 $
b1011 )
b1011 '
#600
0,
0!
0+
1:
11
14
17
b1111 "
b1111 .
0-
00
03
16
b1100 $
b1100 )
b1100 '
#610
1!
0:
1-
07
1,
04
1+
01
b0 "
b0 .
10
b1101 $
b1101 )
b1101 '
#620
0+
11
04
b1 "
b1 .
00
13
b1110 $
b1110 )
b1110 '
#630
14
1+
01
b10 "
b10 .
10
b1111 $
b1111 )
b1111 '
#640
0-
04
17
0+
0,
0:
b100 "
b100 .
0!
00
03
06
09
0/
02
15
b0 $
b0 )
b100 #
b100 (
b100 &
b0 '
#650
11
b101 "
b101 .
10
b1 $
b1 )
b1 '
#660
01
14
b110 "
b110 .
00
13
b10 $
b10 )
b10 '
#670
11
b111 "
b111 .
10
b11 $
b11 )
b11 '
#680
1:
1-
01
04
07
b1000 "
b1000 .
00
03
16
b100 $
b100 )
b100 '
#690
11
b1001 "
b1001 .
10
b101 $
b101 )
b101 '
#700
01
14
b1010 "
b1010 .
00
13
b110 $
b110 )
b110 '
#710
11
b1011 "
b1011 .
10
b111 $
b111 )
b111 '
#720
0-
01
04
17
1:
b1100 "
b1100 .
0!
00
03
06
19
b1000 $
b1000 )
b1000 '
#730
11
b1101 "
b1101 .
10
b1001 $
b1001 )
b1001 '
#740
01
14
b1110 "
b1110 .
00
13
b1010 $
b1010 )
b1010 '
#750
11
b1111 "
b1111 .
10
b1011 $
b1011 )
b1011 '
#760
1!
0:
1-
01
04
07
b0 "
b0 .
00
03
16
b1100 $
b1100 )
b1100 '
#770
11
b1 "
b1 .
10
b1101 $
b1101 )
b1101 '
#780
01
14
b10 "
b10 .
00
13
b1110 $
b1110 )
b1110 '
#790
11
b11 "
b11 .
10
b1111 $
b1111 )
b1111 '
#800
0-
04
17
0:
b101 "
b101 .
0!
00
03
06
09
1/
b0 $
b0 )
b101 #
b101 (
b101 &
b0 '
#810
14
1+
01
b110 "
b110 .
10
b1 $
b1 )
b1 '
#820
0:
0-
0+
17
11
14
b111 "
b111 .
0,
00
13
b10 $
b10 )
b10 '
#830
1:
1-
07
1,
04
1+
01
b1000 "
b1000 .
10
b11 $
b11 )
b11 '
#840
0+
11
04
0,
07
b1001 "
b1001 .
00
03
16
b100 $
b100 )
b100 '
#850
14
1+
01
b1010 "
b1010 .
10
b101 $
b101 )
b101 '
#860
0+
07
11
14
b1011 "
b1011 .
0,
00
13
b110 $
b110 )
b110 '
#870
17
1,
04
1+
01
b1100 "
b1100 .
10
b111 $
b111 )
b111 '
#880
0-
0+
11
04
0,
17
1:
b1101 "
b1101 .
0!
00
03
06
19
b1000 $
b1000 )
b1000 '
#890
14
1+
01
b1110 "
b1110 .
10
b1001 $
b1001 )
b1001 '
#900
0!
1:
0-
0+
17
11
14
b1111 "
b1111 .
0,
00
13
b1010 $
b1010 )
b1010 '
#910
1!
0:
1-
07
1,
04
1+
01
b0 "
b0 .
10
b1011 $
b1011 )
b1011 '
#920
0+
11
04
0,
07
b1 "
b1 .
00
03
16
b1100 $
b1100 )
b1100 '
#930
14
1+
01
b10 "
b10 .
10
b1101 $
b1101 )
b1101 '
#940
0+
07
11
14
b11 "
b11 .
0,
00
13
b1110 $
b1110 )
b1110 '
#950
17
1,
04
1+
01
b100 "
b100 .
10
b1111 $
b1111 )
b1111 '
#960
0-
0,
14
0+
17
0:
b110 "
b110 .
0!
00
03
06
09
0/
12
b0 $
b0 )
b110 #
b110 (
b110 &
b0 '
#970
11
b111 "
b111 .
10
b1 $
b1 )
b1 '
#980
1:
1-
07
1,
01
04
b1000 "
b1000 .
00
13
b10 $
b10 )
b10 '
#990
11
b1001 "
b1001 .
10
b11 $
b11 )
b11 '
#1000
0,
01
14
07
b1010 "
b1010 .
00
03
16
b100 $
b100 )
b100 '
#1010
11
b1011 "
b1011 .
10
b101 $
b101 )
b101 '
#1020
17
1,
01
04
b1100 "
b1100 .
00
13
b110 $
b110 )
b110 '
#1030
11
b1101 "
b1101 .
10
b111 $
b111 )
b111 '
#1040
0-
0,
01
14
17
1:
b1110 "
b1110 .
0!
00
03
06
19
b1000 $
b1000 )
b1000 '
#1050
11
b1111 "
b1111 .
10
b1001 $
b1001 )
b1001 '
#1060
1!
0:
1-
07
1,
01
04
b0 "
b0 .
00
13
b1010 $
b1010 )
b1010 '
#1070
11
b1 "
b1 .
10
b1011 $
b1011 )
b1011 '
#1080
0,
01
14
07
b10 "
b10 .
00
03
16
b1100 $
b1100 )
b1100 '
#1090
11
b11 "
b11 .
10
b1101 $
b1101 )
b1101 '
#1100
17
1,
01
04
b100 "
b100 .
00
13
b1110 $
b1110 )
b1110 '
#1110
11
b101 "
b101 .
10
b1111 $
b1111 )
b1111 '
#1120
0-
0,
14
17
0:
b111 "
b111 .
0!
00
03
06
09
1/
b0 $
b0 )
b111 #
b111 (
b111 &
b0 '
#1130
1:
1-
07
1,
04
1+
01
b1000 "
b1000 .
10
b1 $
b1 )
b1 '
#1140
0+
11
04
b1001 "
b1001 .
00
13
b10 $
b10 )
b10 '
#1150
14
1+
01
b1010 "
b1010 .
10
b11 $
b11 )
b11 '
#1160
0,
0+
11
14
07
b1011 "
b1011 .
00
03
16
b100 $
b100 )
b100 '
#1170
17
1,
04
1+
01
b1100 "
b1100 .
10
b101 $
b101 )
b101 '
#1180
0+
11
04
b1101 "
b1101 .
00
13
b110 $
b110 )
b110 '
#1190
14
1+
01
b1110 "
b1110 .
10
b111 $
b111 )
b111 '
#1200
0-
0,
0+
11
14
17
1:
b1111 "
b1111 .
0!
00
03
06
19
b1000 $
b1000 )
b1000 '
#1210
1!
0:
1-
07
1,
04
1+
01
b0 "
b0 .
10
b1001 $
b1001 )
b1001 '
#1220
0+
11
04
b1 "
b1 .
00
13
b1010 $
b1010 )
b1010 '
#1230
14
1+
01
b10 "
b10 .
10
b1011 $
b1011 )
b1011 '
#1240
0,
0+
11
14
07
b11 "
b11 .
00
03
16
b1100 $
b1100 )
b1100 '
#1250
17
1,
04
1+
01
b100 "
b100 .
10
b1101 $
b1101 )
b1101 '
#1260
0+
11
04
b101 "
b101 .
00
13
b1110 $
b1110 )
b1110 '
#1270
14
1+
01
b110 "
b110 .
10
b1111 $
b1111 )
b1111 '
#1280
0!
04
07
1:
b1000 "
b1000 .
0+
0,
0-
00
03
06
09
0/
02
05
18
b0 $
b0 )
b1000 #
b1000 (
b1000 &
b0 '
#1290
11
b1001 "
b1001 .
10
b1 $
b1 )
b1 '
#1300
01
14
b1010 "
b1010 .
00
13
b10 $
b10 )
b10 '
#1310
11
b1011 "
b1011 .
10
b11 $
b11 )
b11 '
#1320
01
04
17
b1100 "
b1100 .
00
03
16
b100 $
b100 )
b100 '
#1330
11
b1101 "
b1101 .
10
b101 $
b101 )
b101 '
#1340
01
14
b1110 "
b1110 .
00
13
b110 $
b110 )
b110 '
#1350
11
b1111 "
b1111 .
10
b111 $
b111 )
b111 '
#1360
1!
01
04
07
0:
b0 "
b0 .
00
03
06
19
b1000 $
b1000 )
b1000 '
#1370
11
b1 "
b1 .
10
b1001 $
b1001 )
b1001 '
#1380
01
14
b10 "
b10 .
00
13
b1010 $
b1010 )
b1010 '
#1390
11
b11 "
b11 .
10
b1011 $
b1011 )
b1011 '
#1400
01
04
17
b100 "
b100 .
00
03
16
b1100 $
b1100 )
b1100 '
#1410
11
b101 "
b101 .
10
b1101 $
b1101 )
b1101 '
#1420
01
14
b110 "
b110 .
00
13
b1110 $
b1110 )
b1110 '
#1430
11
b111 "
b111 .
10
b1111 $
b1111 )
b1111 '
#1440
0!
04
07
1:
b1001 "
b1001 .
00
03
06
09
1/
b0 $
b0 )
b1001 #
b1001 (
b1001 &
b0 '
#1450
14
1+
01
b1010 "
b1010 .
10
b1 $
b1 )
b1 '
#1460
0+
07
11
14
b1011 "
b1011 .
0,
00
13
b10 $
b10 )
b10 '
#1470
17
1,
04
1+
01
b1100 "
b1100 .
10
b11 $
b11 )
b11 '
#1480
0!
0+
1:
11
04
0,
17
b1101 "
b1101 .
0-
00
03
16
b100 $
b100 )
b100 '
#1490
14
1+
01
b1110 "
b1110 .
10
b101 $
b101 )
b101 '
#1500
0!
1:
0-
0+
17
11
14
b1111 "
b1111 .
0,
00
13
b110 $
b110 )
b110 '
#1510
1!
0:
1-
07
1,
04
1+
01
b0 "
b0 .
10
b111 $
b111 )
b111 '
#1520
0+
11
04
0,
07
0-
0:
b1 "
b1 .
00
03
06
19
b1000 $
b1000 )
b1000 '
#1530
14
1+
01
b10 "
b10 .
10
b1001 $
b1001 )
b1001 '
#1540
0+
07
11
14
b11 "
b11 .
0,
00
13
b1010 $
b1010 )
b1010 '
#1550
17
1,
04
1+
01
b100 "
b100 .
10
b1011 $
b1011 )
b1011 '
#1560
0+
0:
11
04
0,
17
b101 "
b101 .
0-
00
03
16
b1100 $
b1100 )
b1100 '
#1570
14
1+
01
b110 "
b110 .
10
b1101 $
b1101 )
b1101 '
#1580
0:
0-
0+
17
11
14
b111 "
b111 .
0,
00
13
b1110 $
b1110 )
b1110 '
#1590
1:
1-
07
1,
04
1+
01
b1000 "
b1000 .
10
b1111 $
b1111 )
b1111 '
#1600
0,
0!
14
0+
07
0-
1:
b1010 "
b1010 .
00
03
06
09
0/
12
b0 $
b0 )
b1010 #
b1010 (
b1010 &
b0 '
#1610
11
b1011 "
b1011 .
10
b1 $
b1 )
b1 '
#1620
17
1,
01
04
b1100 "
b1100 .
00
13
b10 $
b10 )
b10 '
#1630
11
b1101 "
b1101 .
10
b11 $
b11 )
b11 '
#1640
0!
0,
1:
01
14
17
b1110 "
b1110 .
0-
00
03
16
b100 $
b100 )
b100 '
#1650
11
b1111 "
b1111 .
10
b101 $
b101 )
b101 '
#1660
1!
0:
1-
07
1,
01
04
b0 "
b0 .
00
13
b110 $
b110 )
b110 '
#1670
11
b1 "
b1 .
10
b111 $
b111 )
b111 '
#1680
0,
01
14
07
0-
0:
b10 "
b10 .
00
03
06
19
b1000 $
b1000 )
b1000 '
#1690
11
b11 "
b11 .
10
b1001 $
b1001 )
b1001 '
#1700
17
1,
01
04
b100 "
b100 .
00
13
b1010 $
b1010 )
b1010 '
#1710
11
b101 "
b101 .
10
b1011 $
b1011 )
b1011 '
#1720
0,
0:
01
14
17
b110 "
b110 .
0-
00
03
16
b1100 $
b1100 )
b1100 '
#1730
11
b111 "
b111 .
10
b1101 $
b1101 )
b1101 '
#1740
1:
1-
07
1,
01
04
b1000 "
b1000 .
00
13
b1110 $
b1110 )
b1110 '
#1750
11
b1001 "
b1001 .
10
b1111 $
b1111 )
b1111 '
#1760
0!
0,
14
07
0-
1:
b1011 "
b1011 .
00
03
06
09
1/
b0 $
b0 )
b1011 #
b1011 (
b1011 &
b0 '
#1770
17
1,
04
1+
01
b1100 "
b1100 .
10
b1 $
b1 )
b1 '
#1780
0+
11
04
b1101 "
b1101 .
00
13
b10 $
b10 )
b10 '
#1790
14
1+
01
b1110 "
b1110 .
10
b11 $
b11 )
b11 '
#1800
0,
0!
0+
1:
11
14
17
b1111 "
b1111 .
0-
00
03
16
b100 $
b100 )
b100 '
#1810
1!
0:
1-
07
1,
04
1+
01
b0 "
b0 .
10
b101 $
b101 )
b101 '
#1820
0+
11
04
b1 "
b1 .
00
13
b110 $
b110 )
b110 '
#1830
14
1+
01
b10 "
b10 .
10
b111 $
b111 )
b111 '
#1840
0,
0+
11
14
07
0-
0:
b11 "
b11 .
00
03
06
19
b1000 $
b1000 )
b1000 '
#1850
17
1,
04
1+
01
b100 "
b100 .
10
b1001 $
b1001 )
b1001 '
#1860
0+
11
04
b101 "
b101 .
00
13
b1010 $
b1010 )
b1010 '
#1870
14
1+
01
b110 "
b110 .
10
b1011 $
b1011 )
b1011 '
#1880
0,
0+
0:
11
14
17
b111 "
b111 .
0-
00
03
16
b1100 $
b1100 )
b1100 '
#1890
1:
1-
07
1,
04
1+
01
b1000 "
b1000 .
10
b1101 $
b1101 )
b1101 '
#1900
0+
11
04
b1001 "
b1001 .
00
13
b1110 $
b1110 )
b1110 '
#1910
14
1+
01
b1010 "
b1010 .
10
b1111 $
b1111 )
b1111 '
#1920
0!
0-
04
17
0+
0,
1:
b1100 "
b1100 .
00
03
06
09
0/
02
15
b0 $
b0 )
b1100 #
b1100 (
b1100 &
b0 '
#1930
11
b1101 "
b1101 .
10
b1 $
b1 )
b1 '
#1940
01
14
b1110 "
b1110 .
00
13
b10 $
b10 )
b10 '
#1950
11
b1111 "
b1111 .
10
b11 $
b11 )
b11 '
#1960
1!
0:
1-
01
04
07
b0 "
b0 .
00
03
16
b100 $
b100 )
b100 '
#1970
11
b1 "
b1 .
10
b101 $
b101 )
b101 '
#1980
01
14
b10 "
b10 .
00
13
b110 $
b110 )
b110 '
#1990
11
b11 "
b11 .
10
b111 $
b111 )
b111 '
#2000
0-
01
04
17
0:
b100 "
b100 .
00
03
06
19
b1000 $
b1000 )
b1000 '
#2010
11
b101 "
b101 .
10
b1001 $
b1001 )
b1001 '
#2020
01
14
b110 "
b110 .
00
13
b1010 $
b1010 )
b1010 '
#2030
11
b111 "
b111 .
10
b1011 $
b1011 )
b1011 '
#2040
1:
1-
01
04
07
b1000 "
b1000 .
00
03
16
b1100 $
b1100 )
b1100 '
#2050
11
b1001 "
b1001 .
10
b1101 $
b1101 )
b1101 '
#2060
01
14
b1010 "
b1010 .
00
13
b1110 $
b1110 )
b1110 '
#2070
11
b1011 "
b1011 .
10
b1111 $
b1111 )
b1111 '
#2080
0!
0-
04
17
1:
b1101 "
b1101 .
00
03
06
09
1/
b0 $
b0 )
b1101 #
b1101 (
b1101 &
b0 '
#2090
14
1+
01
b1110 "
b1110 .
10
b1 $
b1 )
b1 '
#2100
0!
1:
0-
0+
17
11
14
b1111 "
b1111 .
0,
00
13
b10 $
b10 )
b10 '
#2110
1!
0:
1-
07
1,
04
1+
01
b0 "
b0 .
10
b11 $
b11 )
b11 '
#2120
0+
11
04
0,
07
b1 "
b1 .
00
03
16
b100 $
b100 )
b100 '
#2130
14
1+
01
b10 "
b10 .
10
b101 $
b101 )
b101 '
#2140
0+
07
11
14
b11 "
b11 .
0,
00
13
b110 $
b110 )
b110 '
#2150
17
1,
04
1+
01
b100 "
b100 .
10
b111 $
b111 )
b111 '
#2160
0-
0+
11
04
0,
17
0:
b101 "
b101 .
00
03
06
19
b1000 $
b1000 )
b1000 '
#2170
14
1+
01
b110 "
b110 .
10
b1001 $
b1001 )
b1001 '
#2180
0:
0-
0+
17
11
14
b111 "
b111 .
0,
00
13
b1010 $
b1010 )
b1010 '
#2190
1:
1-
07
1,
04
1+
01
b1000 "
b1000 .
10
b1011 $
b1011 )
b1011 '
#2200
0+
11
04
0,
07
b1001 "
b1001 .
00
03
16
b1100 $
b1100 )
b1100 '
#2210
14
1+
01
b1010 "
b1010 .
10
b1101 $
b1101 )
b1101 '
#2220
0+
07
11
14
b1011 "
b1011 .
0,
00
13
b1110 $
b1110 )
b1110 '
#2230
17
1,
04
1+
01
b1100 "
b1100 .
10
b1111 $
b1111 )
b1111 '
#2240
0!
0-
0,
14
0+
17
1:
b1110 "
b1110 .
00
03
06
09
0/
12
b0 $
b0 )
b1110 #
b1110 (
b1110 &
b0 '
#2250
11
b1111 "
b1111 .
10
b1 $
b1 )
b1 '
#2260
1!
0:
1-
07
1,
01
04
b0 "
b0 .
00
13
b10 $
b10 )
b10 '
#2270
11
b1 "
b1 .
10
b11 $
b11 )
b11 '
#2280
0,
01
14
07
b10 "
b10 .
00
03
16
b100 $
b100 )
b100 '
#2290
11
b11 "
b11 .
10
b101 $
b101 )
b101 '
#2300
17
1,
01
04
b100 "
b100 .
00
13
b110 $
b110 )
b110 '
#2310
11
b101 "
b101 .
10
b111 $
b111 )
b111 '
#2320
0-
0,
01
14
17
0:
b110 "
b110 .
00
03
06
19
b1000 $
b1000 )
b1000 '
#2330
11
b111 "
b111 .
10
b1001 $
b1001 )
b1001 '
#2340
1:
1-
07
1,
01
04
b1000 "
b1000 .
00
13
b1010 $
b1010 )
b1010 '
#2350
11
b1001 "
b1001 .
10
b1011 $
b1011 )
b1011 '
#2360
0,
01
14
07
b1010 "
b1010 .
00
03
16
b1100 $
b1100 )
b1100 '
#2370
11
b1011 "
b1011 .
10
b1101 $
b1101 )
b1101 '
#2380
17
1,
01
04
b1100 "
b1100 .
00
13
b1110 $
b1110 )
b1110 '
#2390
11
b1101 "
b1101 .
10
b1111 $
b1111 )
b1111 '
#2400
0!
0-
0,
14
17
1:
b1111 "
b1111 .
00
03
06
09
1/
b0 $
b0 )
b1111 #
b1111 (
b1111 &
b0 '
#2410
1!
0:
1-
07
1,
04
1+
01
b0 "
b0 .
10
b1 $
b1 )
b1 '
#2420
0+
11
04
b1 "
b1 .
00
13
b10 $
b10 )
b10 '
#2430
14
1+
01
b10 "
b10 .
10
b11 $
b11 )
b11 '
#2440
0,
0+
11
14
07
b11 "
b11 .
00
03
16
b100 $
b100 )
b100 '
#2450
17
1,
04
1+
01
b100 "
b100 .
10
b101 $
b101 )
b101 '
#2460
0+
11
04
b101 "
b101 .
00
13
b110 $
b110 )
b110 '
#2470
14
1+
01
b110 "
b110 .
10
b111 $
b111 )
b111 '
#2480
0-
0,
0+
11
14
17
0:
b111 "
b111 .
00
03
06
19
b1000 $
b1000 )
b1000 '
#2490
1:
1-
07
1,
04
1+
01
b1000 "
b1000 .
10
b1001 $
b1001 )
b1001 '
#2500
0+
11
04
b1001 "
b1001 .
00
13
b1010 $
b1010 )
b1010 '
#2510
14
1+
01
b1010 "
b1010 .
10
b1011 $
b1011 )
b1011 '
#2520
0,
0+
11
14
07
b1011 "
b1011 .
00
03
16
b1100 $
b1100 )
b1100 '
#2530
17
1,
04
1+
01
b1100 "
b1100 .
10
b1101 $
b1101 )
b1101 '
#2540
0+
11
04
b1101 "
b1101 .
00
13
b1110 $
b1110 )
b1110 '
#2550
14
1+
01
b1110 "
b1110 .
10
b1111 $
b1111 )
b1111 '
#2560
04
07
0:
0+
0,
0-
0!
00
03
06
09
0/
02
05
08
11
b1 "
b1 .
b0 $
b0 )
b0 #
b0 (
1%
1*
b0 &
b0 '
#2570
14
01
b10 "
b10 .
1+
10
b1 $
b1 )
b1 '
#2580
07
11
0+
14
b11 "
b11 .
0,
00
13
b10 $
b10 )
b10 '
#2590
17
1,
04
01
b100 "
b100 .
1+
10
b11 $
b11 )
b11 '
#2600
0:
11
0+
04
0,
17
b101 "
b101 .
0-
00
03
16
b100 $
b100 )
b100 '
#2610
14
01
b110 "
b110 .
1+
10
b101 $
b101 )
b101 '
#2620
0:
0-
17
11
0+
14
b111 "
b111 .
0,
00
13
b110 $
b110 )
b110 '
#2630
1:
1-
07
1,
04
01
b1000 "
b1000 .
1+
10
b111 $
b111 )
b111 '
#2640
11
0+
04
0,
07
0-
1:
b1001 "
b1001 .
0!
00
03
06
19
b1000 $
b1000 )
b1000 '
#2650
14
01
b1010 "
b1010 .
1+
10
b1001 $
b1001 )
b1001 '
#2660
07
11
0+
14
b1011 "
b1011 .
0,
00
13
b1010 $
b1010 )
b1010 '
#2670
17
1,
04
01
b1100 "
b1100 .
1+
10
b1011 $
b1011 )
b1011 '
#2680
0!
1:
11
0+
04
0,
17
b1101 "
b1101 .
0-
00
03
16
b1100 $
b1100 )
b1100 '
#2690
14
01
b1110 "
b1110 .
1+
10
b1101 $
b1101 )
b1101 '
#2700
0!
1:
0-
17
11
0+
14
b1111 "
b1111 .
0,
00
13
b1110 $
b1110 )
b1110 '
#2710
1!
0:
1-
07
1,
04
01
b0 "
b0 .
1+
10
b1111 $
b1111 )
b1111 '
#2720
14
0,
07
0-
0:
b10 "
b10 .
0!
00
03
06
09
1/
b0 $
b0 )
b1 #
b1 (
b1 &
b0 '
#2730
11
b11 "
b11 .
10
b1 $
b1 )
b1 '
#2740
17
01
04
b100 "
b100 .
1,
00
13
b10 $
b10 )
b10 '
#2750
11
b101 "
b101 .
10
b11 $
b11 )
b11 '
#2760
0:
01
14
0,
17
b110 "
b110 .
0-
00
03
16
b100 $
b100 )
b100 '
#2770
11
b111 "
b111 .
10
b101 $
b101 )
b101 '
#2780
1:
1-
07
01
04
b1000 "
b1000 .
1,
00
13
b110 $
b110 )
b110 '
#2790
11
b1001 "
b1001 .
10
b111 $
b111 )
b111 '
#2800
01
14
0,
07
0-
1:
b1010 "
b1010 .
0!
00
03
06
19
b1000 $
b1000 )
b1000 '
#2810
11
b1011 "
b1011 .
10
b1001 $
b1001 )
b1001 '
#2820
17
01
04
b1100 "
b1100 .
1,
00
13
b1010 $
b1010 )
b1010 '
#2830
11
b1101 "
b1101 .
10
b1011 $
b1011 )
b1011 '
#2840
0!
1:
01
14
0,
17
b1110 "
b1110 .
0-
00
03
16
b1100 $
b1100 )
b1100 '
#2850
11
b1111 "
b1111 .
10
b1101 $
b1101 )
b1101 '
#2860
1!
0:
1-
07
01
04
b0 "
b0 .
1,
00
13
b1110 $
b1110 )
b1110 '
#2870
11
b1 "
b1 .
10
b1111 $
b1111 )
b1111 '
#2880
0,
14
0+
07
0-
0:
b11 "
b11 .
0!
00
03
06
09
0/
12
b0 $
b0 )
b10 #
b10 (
b10 &
b0 '
#2890
17
1,
04
01
b100 "
b100 .
1+
10
b1 $
b1 )
b1 '
#2900
11
0+
04
b101 "
b101 .
00
13
b10 $
b10 )
b10 '
