REGISTER/SHIFT/UNIVERSAL_SHIFT/uni_shift_reg.v
module universal_shift_reg (
    input  wire        clk,
    input  wire        rst,
    input  wire [1:0]  mode,      // control signal
    input  wire        s_left,    // serial input for left shift
    input  wire        s_right,   // serial input for right shift
    input  wire [3:0]  par_in,    // parallel data input
    output reg  [3:0]  q          // register output
);

    always @(posedge clk or posedge rst) begin
        if (rst)
            q <= 4'b0000;
        else begin
            case (mode)
                2'b00: q <= q;                     // Hold
                2'b01: q <= {s_right, q[3:1]};    // Shift Right (bring in s_right)
                2'b10: q <= {q[2:0], s_left};     // Shift Left (bring in s_left)
                2'b11: q <= par_in;                // Parallel Load
                default: q <= q;
            endcase
        end
    end

endmodule

REGISTER/SHIFT/UNIVERSAL_SHIFT/uni_shift_regTB.v
module tb_universal_shift_reg;
    // Signals
    reg clk = 0, rst, s_left, s_right;
    reg [1:0] mode;
    reg [3:0] par_in;
    wire [3:0] q;

    // DUT instantiation
    universal_shift_reg dut (
        .clk(clk), .rst(rst), .mode(mode),
        .s_left(s_left), .s_right(s_right),
        .par_in(par_in), .q(q)
    );

    // Clock generation: 10 time units period
    always #5 clk = ~clk;

    initial begin
        // 1. RESET
        rst = 1; mode = 2'b00; s_left = 0; s_right = 0; par_in = 4'b0000; 
        #10 rst = 0;

        // 2. PARALLEL LOAD
        par_in = 4'b1101; mode = 2'b11; s_left = 0; s_right = 0; #10;

        // 3. CLEAR par_in explicitly while HOLDing value in register
        mode = 2'b00; par_in = 4'b0000; s_left = 0; s_right = 0; #10;

        // 4. HOLD (register keeps value)
        mode = 2'b00; s_left = 0; s_right = 0; #10;

        // 5. SHIFT RIGHT
        mode = 2'b01; s_left = 0; s_right = 1; #10;

        // 6. SHIFT LEFT
        mode = 2'b10; s_left = 1; s_right = 0; #10;

        $finish;
    end

    // Monitor signals
    initial $monitor("T=%t | clk=%b rst=%b | mode=%b | s_left=%b s_right=%b | par_in=%b | q=%b",
                     $time, clk, rst, mode, s_left, s_right, par_in, q);
endmodule

REGISTER/SHIFT/UNIVERSAL_SHIFT/uni_shift_reg.vcd
$date
	Sat Nov 15 11:38:28 2025
$end
$version
	Icarus Verilog
$end
$timescale
	1s
$end
$scope module tb_universal_shift_reg $end
$var wire 4 ! q [3:0] $end
$var reg 1 " clk $end
$var reg 2 # mode [1:0] $end
$var reg 4 $ par_in [3:0] $end
$var reg 1 % rst $end
$var reg 1 & s_left $end
$var reg 1 ' s_right $end
$scope module dut $end
$var wire 1 ( clk $end
$var wire 2 ) mode [1:0] $end
$var wire 4 * par_in [3:0] $end
$var wire 1 + rst $end
$var wire 1 , s_left $end
$var wire 1 - s_right $end
$var reg 4 . q [3:0] $end
$upscope $end
$upscope $end
$enddefinitions $end
#0
$dumpvars
b0 .
0-
0,
1+
b0 *
b0 )
0(
0'
0&
1%
b0 $
b0 #
0"
b0 !
$end
#5
1"
1(
#10
0"
0(
b11 #
b11 )
b1101 $
b1101 *
0%
0+
#15
b1101 .
b1101 !
1"
1(
#20
0"
0(
b0 #
b0 )
#25
1"
1(
#30
0"
0(
b1 #
b1 )
1&
1,
#35
b1110 .
b1110 !
1"
1(
#40
0"
0(
#45
b1111 .
b1111 !
1"
1(
#50
0"
0(
b10 #
b10 )
#55
b1110 .
b1110 !
1"
1(
#60
0"
0(
#65
b1100 .
b1100 !
1"
1(
#70
0"
0(
b11 #
b11 )
b101 $
b101 *
#75
b101 .
b101 !
1"
1(
