ENCODER/encoder.v
module encoder8_3(
    input wire [7:0] i,
    output wire [2:0] y
);
    // Logic operations for 8-to-3 encoder
    assign y[2] = i[4] | i[5] | i[6] | i[7];
    assign y[1] = i[2] | i[3] | i[6] | i[7];
    assign y[0] = i[1] | i[3] | i[5] | i[7];
endmodule

ENCODER/encoderTB.v
module encoder8_3TB();
    reg [7:0] i;
    wire [2:0] y;
    integer j;

    encoder8_3 dut (.i(i),.y(y));

    initial begin
        $dumpfile("encoder.vcd");
        $dumpvars(0, encoder8_3TB);
        i = 8'b00000000;

        for(j=0; j<8; j=j+1) begin
            i = 1 << j;
            #10;
        end
    end

    initial
        $monitor("input i=%8b | output y=%3b", i, y);
    initial 
    #100 $finish();
    endmodule

ENCODER/encoder.vcd
$date
	Thu Sep 25 05:48:37 2025
$end
$version
	Icarus Verilog
$end
$timescale
	1s
$end
$scope module encoder8_3TB $end
$var wire 3 ! y [2:0] $end
$var reg 8 " i [7:0] $end
$var integer 32 # j [31:0] $end
$scope module dut $end
$var wire 8 $ i [7:0] $end
$var wire 3 % y [2:0] $end
$upscope $end
$upscope $end
$enddefinitions $end
#0
$dumpvars
b0 %
b1 $
b0 #
b1 "
b0 !
$end
#10
b1 !
b1 %
b10 "
b10 $
b1 #
#20
b10 !
b10 %
b100 "
b100 $
b10 #
#30
b11 !
b11 %
b1000 "
b1000 $
b11 #
#40
b100 !
b100 %
b10000 "
b10000 $
b100 #
#50
b101 !
b101 %
b100000 "
b100000 $
b101 #
#60
b110 !
b110 %
b1000000 "
b1000000 $
b110 #
#70
b111 !
b111 %
b10000000 "
b10000000 $
b111 #
#80
b1000 #
