REGISTER/SHIFT/Shift_register.v
module shift_register(
    input clock, input reset, input serial_in,
    output reg [3:0] q
);
    always @(posedge clock) begin
        if (reset)
            q <= 4'b0000;
        else
            q <= {q[2:0], serial_in};
    end
endmodule

REGISTER/SHIFT/Shift_registerTB.v
`timescale 1ns/1ps
module shift_register_tb();
    reg clock, reset, serial_in;
    wire [3:0] q;

    shift_register uut(
        .clock(clock),
        .reset(reset),
        .serial_in(serial_in),
        .q(q)
    );

    initial begin
        clock = 0;
        forever #5 clock = ~clock;
    end

    initial begin
        $dumpfile("shift_register.vcd");
        $dumpvars(0, shift_register_tb);

        $monitor("Time= %0t| Reset=%b | Serial_in=%b | Output=%b", $time, reset, serial_in, q);

        reset = 1; serial_in = 0; #10 reset = 0;
        serial_in = 1; #10;
        serial_in = 0; #10;
        serial_in = 1; #10;
        serial_in = 1; #10;
        serial_in = 0; #10;
        #20;
        $finish;
    end
endmodule

REGISTER/SHIFT/Shift_register.vcd
$date
	Thu Oct 23 20:43:32 2025
$end
$version
	Icarus Verilog
$end
$timescale
	1ps
$end
$scope module shift_register_tb $end
$var wire 4 ! q [3:0] $end
$var reg 1 " clock $end
$var reg 1 # reset $end
$var reg 1 $ serial_in $end
$scope module uut $end
$var wire 1 % clock $end
$var wire 1 & reset $end
$var wire 1 ' serial_in $end
$var reg 4 ( q [3:0] $end
$upscope $end
$upscope $end
$enddefinitions $end
#0
$dumpvars
bx (
0'
1&
0%
0$
1#
0"
bx !
$end
#5000
b0 (
b0 !
1"
1%
#10000
0"
0%
1$
1'
0#
0&
#15000
b1 (
b1 !
1"
1%
#20000
0"
0%
0$
0'
#25000
b10 (
b10 !
1"
1%
#30000
0"
0%
1$
1'
#35000
b101 (
b101 !
1"
1%
#40000
0"
0%
#45000
b1011 (
b1011 !
1"
1%
#50000
0"
0%
0$
0'
#55000
b110 (
b110 !
1"
1%
#60000
0"
0%
#65000
b1100 (
b1100 !
1"
1%
#70000
0"
0%
#75000
b1000 (
b1000 !
1"
1%
