DECODER/decoder.v
// 2-to-4 Decoder with enable
module decoder2_4(
    input en, // enable
    input a,  // input a (was i0)
    input b,  // input b (was i1)
    output [3:0] y
);
    // Output logic: y[0] to y[3] are active based on enable and inputs
    assign y[0] = (en & ~a & ~b);
    assign y[1] = (en & ~a &  b);
    assign y[2] = (en &  a & ~b);
    assign y[3] = (en &  a &  b);
endmodule

DECODER/decodeTB.v
module decoder2_4TB();

    reg en,a,b;
    wire [3:0]y;
    integer i;

    decoder2_4 dut (.en(en),.a(a),.b(b),.y(y));

    initial
    begin
        $dumpfile("decoder.vcd");
        $dumpvars(0,decoder2_4TB);
    en=0; a=0; b=0;
 

        for(i=0; i<8; i=i+1)
        begin
           {en,a,b}=i;
            #10;
        end
    end

    initial $monitor(" time=%4t|en=%b |a=%b |b=%b |y=%b",$time,en,a,b,y);
    initial #100 $finish();
 
endmodule

DECODER/decoder.vcd
$date
	Mon Sep 22 10:03:03 2025
$end
$version
	Icarus Verilog
$end
$timescale
	1s
$end
$scope module decoder2_4TB $end
$var wire 4 ! y [3:0] $end
$var reg 1 " a $end
$var reg 1 # b $end
$var reg 1 $ en $end
$var integer 32 % i [31:0] $end
$scope module dut $end
$var wire 1 & a $end
$var wire 1 ' b $end
$var wire 1 ( en $end
$var wire 4 ) y [3:0] $end
$upscope $end
$upscope $end
$enddefinitions $end
#0
$dumpvars
b0 )
0(
0'
0&
b0 %
0$
0#
0"
b0 !
$end
#10
1#
1'
b1 %
#20
1"
1&
0#
0'
b10 %
#30
1#
1'
b11 %
#40
b1 !
b1 )
1$
1(
0"
0&
0#
0'
b100 %
#50
b10 !
b10 )
1#
1'
b101 %
#60
b100 !
b100 )
1"
1&
0#
0'
b110 %
#70
b1000 !
b1000 )
1#
1'
b111 %
#80
b1000 %
