BCD_DECODER/BCDdecode.v
module bcd_to_7seg (
    input  wire [3:0] bcd,    // BCD digit 0–9
    output reg  [6:0] seg     // {a, b, c, d, e, f, g}
);

    always @* begin
        case (bcd)
            4'd0: seg = 7'b1111110; // 0
            4'd1: seg = 7'b0110000; // 1
            4'd2: seg = 7'b1101101; // 2
            4'd3: seg = 7'b1111001; // 3
            4'd4: seg = 7'b0110011; // 4
            4'd5: seg = 7'b1011011; // 5
            4'd6: seg = 7'b1011111; // 6
            4'd7: seg = 7'b1110000; // 7
            4'd8: seg = 7'b1111111; // 8
            4'd9: seg = 7'b1111011; // 9
            default: seg = 7'b0000000; // blank 
        endcase
    end

endmodule

BCD_DECODER/tb.v
`timescale 1ns/1ps

module tb_bcd_to_7seg;

    reg  [3:0] bcd;
    wire [6:0] seg;
    // Instantiate the DUT
    bcd_to_7seg dut (
        .bcd(bcd),
        .seg(seg)
    );
    integer i;
    initial begin
        // Create waveform dump
        $dumpfile("BCDdecode.vcd");
        $dumpvars(0, tb_bcd_to_7seg);

        
        $display("Time\tBCD\tabcdefg");
        $monitor("%0dns\t%0d\t%b", $time, bcd, seg);

       
        for (i = 0; i < 16; i = i + 1) begin
            bcd = i[3:0];
            #10;
        end
        $finish;
    end
endmodule

BCD_DECODER/BCDdecode.vcd
$date
	Sat Sep 27 08:59:06 2025
$end
$version
	Icarus Verilog
$end
$timescale
	1ps
$end
$scope module tb_bcd_to_7seg $end
$var wire 7 ! seg [6:0] $end
$var reg 4 " bcd [3:0] $end
$var integer 32 # i [31:0] $end
$scope module dut $end
$var wire 4 $ bcd [3:0] $end
$var reg 7 % seg [6:0] $end
$upscope $end
$upscope $end
$enddefinitions $end
#0
$dumpvars
b1111110 %
b0 $
b0 #
b0 "
b1111110 !
$end
#10000
b110000 %
b110000 !
b1 "
b1 $
b1 #
#20000
b1101101 %
b1101101 !
b10 "
b10 $
b10 #
#30000
b1111001 %
b1111001 !
b11 "
b11 $
b11 #
#40000
b110011 %
b110011 !
b100 "
b100 $
b100 #
#50000
b1011011 %
b1011011 !
b101 "
b101 $
b101 #
#60000
b1011111 %
b1011111 !
b110 "
b110 $
b110 #
#70000
b1110000 %
b1110000 !
b111 "
b111 $
b111 #
#80000
b1111111 %
b1111111 !
b1000 "
b1000 $
b1000 #
#90000
b1111011 %
b1111011 !
b1001 "
b1001 $
b1001 #
#100000
b0 %
b0 !
b1010 "
b1010 $
b1010 #
#110000
b1011 "
b1011 $
b1011 #
#120000
b1100 "
b1100 $
b1100 #
#130000
b1101 "
b1101 $
b1101 #
#140000
b1110 "
b1110 $
b1110 #
#150000
b1111 "
b1111 $
b1111 #
#160000
b10000 #
