ALU/ALU.v
module alu_4bit(
    input [3:0] a, b,
    input [2:0] select,
    output reg [3:0] y,
    output reg cout
);
    always @(*) begin
        case(select)
            3'b000: {cout, y} = a + b;       // addition
            3'b001: {cout, y} = a - b;       // subtraction
            3'b010: y = a & b;               // and
            3'b011: y = a | b;               // or
            3'b100: y = a ^ b;               // xor
            3'b101: y = ~a;                  // not
            3'b110: y = a + 1;               // increment
            3'b111: y = a - 1;               // decrement
            default: y = 4'b0000;
        endcase
    end
endmodule

ALU/ALU_tb.v
`timescale 1ns/1ps
module alu_4bit_tb();
    reg [3:0] a, b;
    reg [2:0] select;
    wire [3:0] y;
    wire cout;

    alu_4bit uut(
        .a(a),
        .b(b),
        .select(select),
        .y(y),
        .cout(cout)
    );

    initial begin
        $dumpfile("alu_4bit.vcd");
        $dumpvars(0, alu_4bit_tb);
        $monitor("time=%t | a=%b | b=%b | sel=%b | y=%b | cout=%b", $time, a, b, select, y,cout);

        a = 4'b0101; b = 4'b0011;

        select = 3'b000; #10; // addition
        select = 3'b001; #10; // subtraction
        select = 3'b010; #10; // and
        select = 3'b011; #10; // or
        select = 3'b100; #10; // xor
        select = 3'b101; #10; // not
        select = 3'b110; #10; // increment
        select = 3'b111; #10; // decrement

        #10 $finish;
    end
endmodule

ALU/alu_4bit.vcd
$date
	Fri Oct 31 09:15:55 2025
$end
$version
	Icarus Verilog
$end
$timescale
	1ps
$end
$scope module alu_4bit_tb $end
$var wire 1 ! cout $end
$var wire 4 " y [3:0] $end
$var reg 4 # a [3:0] $end
$var reg 4 $ b [3:0] $end
$var reg 3 % select [2:0] $end
$scope module uut $end
$var wire 4 & a [3:0] $end
$var wire 4 ' b [3:0] $end
$var wire 3 ( select [2:0] $end
$var reg 1 ) cout $end
$var reg 4 * y [3:0] $end
$upscope $end
$upscope $end
$enddefinitions $end
#0
$dumpvars
b1000 *
0)
b0 (
b11 '
b101 &
b0 %
b11 $
b101 #
b1000 "
0!
$end
#10000
b10 *
b10 "
b1 %
b1 (
#20000
b1 *
b1 "
b10 %
b10 (
#30000
b111 *
b111 "
b11 %
b11 (
#40000
b110 *
b110 "
b100 %
b100 (
#50000
b1010 *
b1010 "
b101 %
b101 (
#60000
b110 *
b110 "
b110 %
b110 (
#70000
b100 *
b100 "
b111 %
b111 (
