REGISTER/PISO/PISO_shift_register.v

module piso_shift_register(
    input clock,
    input reset,
    input load,
    input [3:0] parallel_in,
    output reg serial_out,
    output reg [3:0] q
);

    always @(posedge clock or posedge reset) begin
        if (reset) begin
            q <= 4'b0000;         
            serial_out <= 0;      
        end
        else if (load) begin
            q <= parallel_in;      // load parallel data
            serial_out <= parallel_in[0]; // LSB immediately
        end
        else begin
            serial_out <= q[0];   // output LSB before shift
            q <= q >> 1;          // shift right
        end
    end

endmodule

REGISTER/PISO/PISO_shift_registerTB.v
`timescale 1ns/1ps
module piso_tb();
    reg clock, reset, load;
    reg [3:0] parallel_in;
    wire serial_out;
    wire [3:0] q;

    piso_shift_register uut(
        .clock(clock),
        .reset(reset),
        .load(load),
        .parallel_in(parallel_in),
        .serial_out(serial_out),
        .q(q)
    );

    initial begin
        clock = 0;
        forever #5 clock = ~clock;
    end

    initial begin
        $dumpfile("Shift_register.vcd");
        $dumpvars(0, piso_tb);
        $monitor("Time=%0t | Load=%b | Parallel_in=%b | Q=%b | Serial_out=%b", 
                  $time, load, parallel_in, q, serial_out);

      
        reset = 1; load = 0; parallel_in = 4'b1011; #10;
        reset = 0;

        // Parallel load
        load = 1; parallel_in = 4'b1011; #10;
        load = 0;

        #50;

        $finish;
    end
endmodule

REGISTER/PISO/SHift_register.vcd
$date
	Sat Oct 25 20:21:59 2025
$end
$version
	Icarus Verilog
$end
$timescale
	1ps
$end
$scope module piso_tb $end
$var wire 4 ! q [3:0] $end
$var wire 1 " serial_out $end
$var reg 1 # clock $end
$var reg 1 $ load $end
$var reg 4 % parallel_in [3:0] $end
$var reg 1 & reset $end
$scope module uut $end
$var wire 1 ' clock $end
$var wire 1 ( load $end
$var wire 4 ) parallel_in [3:0] $end
$var wire 1 * reset $end
$var reg 4 + q [3:0] $end
$var reg 1 , serial_out $end
$upscope $end
$upscope $end
$enddefinitions $end
#0
$dumpvars
0,
b0 +
1*
b1011 )
0(
0'
1&
b1011 %
0$
0#
0"
b0 !
$end
#5000
1#
1'
#10000
0#
0'
1$
1(
0&
0*
#15000
1,
1"
b1011 +
b1011 !
1#
1'
#20000
0#
0'
0$
0(
#25000
b101 +
b101 !
1#
1'
#30000
0#
0'
#35000
b10 +
b10 !
1#
1'
#40000
0#
0'
#45000
b1 +
b1 !
0,
0"
1#
1'
#50000
0#
0'
#55000
b0 +
b0 !
1,
1"
1#
1'
#60000
0#
0'
#65000
0,
0"
1#
1'
